qd/__init__.py
qd/cae/ArrayD3plot.py
qd/cae/Binout.py
qd/cae/D3plot.py
qd/cae/KeyFile.py
qd/cae/Part.py
qd/cae/RawD3plot.py
qd/cae/__init__.py
qd/cae/_dyna_utils.py
qd/cae/dyna.py
qd/cae/dyna_cpp.cp36-win_amd64.pyd
qd/cae/lsda_py3.py
qd/cae/beta/MetaCommunicator.py
qd/cae/beta/__init__.py
qd/cae/beta/meta_remote_control
qd/cae/beta/meta_remote_control.exe
qd/cae/beta/msvcr71.dll
qd/cae/resources/__init__.py
qd/cae/resources/chroma.min.js
qd/cae/resources/html.template
qd/cae/resources/jquery.min.js
qd/cae/resources/jszip.min.js
qd/cae/resources/three.min.js
qd/numerics/__init__.py
qd/numerics/sampling.py
qd-0.8.9.dist-info/LICENSE.txt
qd-0.8.9.dist-info/METADATA
qd-0.8.9.dist-info/WHEEL
qd-0.8.9.dist-info/top_level.txt
qd-0.8.9.dist-info/RECORD
