Metadata-Version: 2.1
Name: qd
Version: 0.8.9
Summary: QD-Engineering Python Library for CAE
Home-page: http://www.qd-eng.de
Author: C. Diez, D. Toewe
Author-email: qd.eng.contact@gmail.com
License: BSD3
Keywords: cae,simulation,engineering,ls-dyna,postprocessing,preprocessing,keyfile,binout
Platform: UNKNOWN
Classifier: Development Status :: 4 - Beta
Classifier: Programming Language :: C++
Classifier: Topic :: Scientific/Engineering
Classifier: Intended Audience :: Science/Research
Classifier: Topic :: Utilities
Classifier: Operating System :: Microsoft :: Windows
Classifier: Operating System :: POSIX :: Linux
Classifier: Programming Language :: Python :: 3.5
Classifier: Programming Language :: Python :: 3.6
Classifier: Programming Language :: Python :: 3.7
Requires-Dist: numpy (>=1.8)
Requires-Dist: diversipy
Requires-Dist: pybind11 (==2.1.1)
Requires-Dist: h5py
